tasker/__init__.py
tasker/command_line_task.py
tasker/function_task.py
tasker/notifier.py
tasker/scheduler.py
tasker/task.py
tasker/util.py
tasker_python-0.1.4.dist-info/LICENSE
tasker_python-0.1.4.dist-info/METADATA
tasker_python-0.1.4.dist-info/WHEEL
tasker_python-0.1.4.dist-info/top_level.txt
tasker_python-0.1.4.dist-info/RECORD
