Metadata-Version: 2.1
Name: tasker-python
Version: 0.1.4
Summary: Simple task automation framework for Python, integrating Rocketry for advanced scheduling and Apprise for multi-platform notifications. Wraps Python functions and shell commands into easily manageable and schedulable units.
Home-page: https://github.com/zigai/tasker
Author: Žiga Ivanšek
Author-email: ziga.ivansek@gmail.com
License: MIT
Keywords: tasker,python,task scheduler,scheduler notifications,cron notifications,rocketry,apprise
Classifier: Programming Language :: Python
Classifier: Programming Language :: Python :: 3 :: Only
Classifier: Programming Language :: Python :: 3.10
Classifier: Programming Language :: Python :: 3.11
Classifier: Programming Language :: Python :: 3.12
Classifier: Topic :: Software Development :: Libraries :: Python Modules
Classifier: Intended Audience :: Developers
Classifier: Operating System :: OS Independent
Classifier: Topic :: Office/Business :: Scheduling
Classifier: License :: OSI Approved :: MIT License
License-File: LICENSE
Requires-Dist: apprise==1.8.0
Requires-Dist: rocketry==2.5.1
Requires-Dist: stdl>=0.5.5
